lod_unit/__init__.py
lod_unit/_version.py
lod_unit/lod_unit.py
lod_unit-1.8.0.dist-info/METADATA
lod_unit-1.8.0.dist-info/WHEEL
lod_unit-1.8.0.dist-info/licenses/LICENSE
lod_unit-1.8.0.dist-info/RECORD
