Metadata-Version: 2.4
Name: lod_unit
Version: 1.8.0
Summary: A simple python library with an astropy unit for λ/D
Project-URL: Homepage, https://github.com/CoreySpohn/lod_unit
Project-URL: Issues, https://github.com/CoreySpohn/lod_unit/issues
Author-email: Corey Spohn <corey.a.spohn@nasa.gov>
License: MIT License
License-File: LICENSE
Classifier: Development Status :: 3 - Alpha
Classifier: Intended Audience :: Science/Research
Classifier: License :: OSI Approved :: MIT License
Classifier: Programming Language :: Python :: 3
Classifier: Topic :: Scientific/Engineering :: Astronomy
Requires-Python: >=3.9
Requires-Dist: astropy>=5.0.0
Provides-Extra: docs
Requires-Dist: myst-parser; extra == 'docs'
Requires-Dist: sphinx; extra == 'docs'
Requires-Dist: sphinx-autoapi; extra == 'docs'
Requires-Dist: sphinx-autodoc-typehints; extra == 'docs'
Requires-Dist: sphinx-book-theme; extra == 'docs'
Provides-Extra: test
Requires-Dist: hypothesis; extra == 'test'
Requires-Dist: nox; extra == 'test'
Requires-Dist: pytest; extra == 'test'
Requires-Dist: pytest-cov; extra == 'test'
